tkmail/__init__.py
tkmail/tkmail.py
tkmail-4.0.3.dist-info/METADATA
tkmail-4.0.3.dist-info/WHEEL
tkmail-4.0.3.dist-info/top_level.txt
tkmail-4.0.3.dist-info/RECORD
