Metadata-Version: 2.1
Name: tkmail
Version: 4.0.3
Summary: Tool send email via SMTP (with retry)
Home-page: https://git.teko.vn/data/libs/smtp-mail
Author: tuan.dv, nhat.nv
Author-email: tuan.dv@teko.vn, nhat.nv@teko.vn
License: UNKNOWN
Platform: UNKNOWN
Classifier: Programming Language :: Python :: 3
Classifier: License :: OSI Approved :: MIT License
Classifier: Operating System :: OS Independent
